hyperprotocols/HYPERTEXT.py
hyperprotocols/TRANSFERPROTOCOLS.py
hyperprotocols/__init__.py
hyperprotocols-0.0.5.dist-info/LICENSE
hyperprotocols-0.0.5.dist-info/METADATA
hyperprotocols-0.0.5.dist-info/WHEEL
hyperprotocols-0.0.5.dist-info/top_level.txt
hyperprotocols-0.0.5.dist-info/RECORD
