Metadata-Version: 2.1
Name: hyperprotocols
Version: 0.0.5
Summary: simple tools for advanced web related actions
Home-page: https://github.com/schizoprada/hyperprotocols
Author: Joel Yisrael
Author-email: joel@sss.bot
Classifier: Programming Language :: Python :: 3
Classifier: License :: OSI Approved :: MIT License
Classifier: Operating System :: OS Independent
Requires-Python: >=3.6
License-File: LICENSE
